AUTHORS
ChangeLog
LICENSE
README.rst
requirements.txt
setup.cfg
setup.py
pyshaker_agent.egg-info/PKG-INFO
pyshaker_agent.egg-info/SOURCES.txt
pyshaker_agent.egg-info/dependency_links.txt
pyshaker_agent.egg-info/entry_points.txt
pyshaker_agent.egg-info/not-zip-safe
pyshaker_agent.egg-info/pbr.json
pyshaker_agent.egg-info/requires.txt
pyshaker_agent.egg-info/top_level.txt
shaker/__init__.py
shaker/lib.py
shaker/version.py
shaker/agent/__init__.py
shaker/agent/agent.py
shaker/engine/__init__.py
shaker/engine/config.py
shaker/engine/deploy.py
shaker/engine/image_builder.py
shaker/engine/messaging.py
shaker/engine/quorum.py
shaker/engine/report.py
shaker/engine/server.py
shaker/engine/sla.py
shaker/engine/utils.py
shaker/engine/aggregators/__init__.py
shaker/engine/aggregators/base.py
shaker/engine/aggregators/traffic.py
shaker/engine/executors/__init__.py
shaker/engine/executors/base.py
shaker/engine/executors/flent.py
shaker/engine/executors/iperf.py
shaker/engine/executors/netperf.py
shaker/engine/executors/shell.py
shaker/openstack/__init__.py
shaker/openstack/clients/__init__.py
shaker/openstack/clients/glance.py
shaker/openstack/clients/heat.py
shaker/openstack/clients/keystone.py
shaker/openstack/clients/neutron.py
shaker/openstack/clients/nova.py
shaker/openstack/clients/openstack.py
shaker/resources/image_builder_templates/centos.yaml
shaker/resources/image_builder_templates/debian.yaml
shaker/resources/image_builder_templates/ubuntu.yaml
shaker/resources/report_templates/interactive.html
shaker/resources/report_templates/json.html
shaker/scenarios/misc/instance_metadata.hot
shaker/scenarios/misc/instance_metadata.yaml
shaker/scenarios/misc/static_agent.yaml
shaker/scenarios/misc/static_agents_pair.yaml
shaker/scenarios/networking/dense_l2.yaml
shaker/scenarios/networking/dense_l3_east_west.yaml
shaker/scenarios/networking/dense_l3_north_south.yaml
shaker/scenarios/networking/full_l2.yaml
shaker/scenarios/networking/full_l3_east_west.yaml
shaker/scenarios/networking/full_l3_north_south.yaml
shaker/scenarios/networking/l2.hot
shaker/scenarios/networking/l3_east_west.hot
shaker/scenarios/networking/l3_north_south.hot
shaker/scenarios/networking/perf_l2.yaml
shaker/scenarios/networking/perf_l3_east_west.yaml
